pgextras/__init__.py
pgextras/sql_constants.py
pgextras-0.1.1.dist-info/DESCRIPTION.rst
pgextras-0.1.1.dist-info/METADATA
pgextras-0.1.1.dist-info/pydist.json
pgextras-0.1.1.dist-info/RECORD
pgextras-0.1.1.dist-info/top_level.txt
pgextras-0.1.1.dist-info/WHEEL
