Metadata-Version: 2.0
Name: pgextras
Version: 0.1.1
Summary: Unofficial Python port of Heroku's pgextras that provides various statistics for a Postgres instance.
Home-page: https://github.com/scottwoodall/python-pgextras
Author: Scott Woodall
Author-email: scott.woodall@gmail.com
License: BSD
Keywords: pgextras
Platform: UNKNOWN
Classifier: Development Status :: 2 - Pre-Alpha
Classifier: Intended Audience :: Developers
Classifier: License :: OSI Approved :: BSD License
Classifier: Natural Language :: English
Classifier: Programming Language :: Python :: 2
Classifier: Programming Language :: Python :: 2.7
Classifier: Programming Language :: Python :: 3
Classifier: Programming Language :: Python :: 3.3
